[{"id": 1, "player": "PAB_3", "time": 0.032116, "empty_cells": 42, "round": 1}, {"id": 1, "player": "MCTS_10000", "time": 10.206118, "empty_cells": 41, "round": 1}, {"id": 1, "player": "PAB_3", "time": 0.037476, "empty_cells": 40, "round": 2}, {"id": 1, "player": "MCTS_10000", "time": 9.534083, "empty_cells": 39, "round": 2}, {"id": 1, "player": "PAB_3", "time": 0.040754, "empty_cells": 38, "round": 3}, {"id": 1, "player": "MCTS_10000", "time": 10.479856, "empty_cells": 37, "round": 3}, {"id": 1, "player": "PAB_3", "time": 0.037197, "empty_cells": 36, "round": 4}, {"id": 1, "player": "MCTS_10000", "time": 8.962708, "empty_cells": 35, "round": 4}, {"id": 1, "player": "PAB_3", "time": 0.029825, "empty_cells": 34, "round": 5}, {"id": 1, "player": "MCTS_10000", "time": 8.350588, "empty_cells": 33, "round": 5}, {"id": 1, "player": "PAB_3", "time": 0.044119, "empty_cells": 32, "round": 6}, {"id": 1, "player": "MCTS_10000", "time": 6.811911, "empty_cells": 31, "round": 6}, {"id": 1, "player": "PAB_3", "time": 0.041834, "empty_cells": 30, "round": 7}, {"id": 1, "player": "MCTS_10000", "time": 5.801349, "empty_cells": 29, "round": 7}, {"id": 1, "player": "PAB_3", "time": 0.043862, "empty_cells": 28, "round": 8}, {"id": 1, "player": "MCTS_10000", "time": 3.794429, "empty_cells": 27, "round": 8}, {"id": 1, "player": "PAB_3", "time": 0.032191, "empty_cells": 26, "round": 9}, {"id": 1, "player": "MCTS_10000", "time": 1.711999, "empty_cells": 25, "round": 9}, {"id": 1, "player": "PAB_3", "time": 0.027659, "empty_cells": 24, "round": 10}, {"id": 1, "player": "MCTS_10000", "time": 1.789451, "empty_cells": 23, "round": 10}, {"id": 2, "player": "PAB_3", "time": 0.038992, "empty_cells": 42, "round": 1}, {"id": 2, "player": "MCTS_10000", "time": 9.991206, "empty_cells": 41, "round": 1}, {"id": 2, "player": "PAB_3", "time": 0.03324, "empty_cells": 40, "round": 2}, {"id": 2, "player": "MCTS_10000", "time": 9.214955, "empty_cells": 39, "round": 2}, {"id": 2, "player": "PAB_3", "time": 0.04476, "empty_cells": 38, "round": 3}, {"id": 2, "player": "MCTS_10000", "time": 9.203636, "empty_cells": 37, "round": 3}, {"id": 2, "player": "PAB_3", "time": 0.044732, "empty_cells": 36, "round": 4}, {"id": 2, "player": "MCTS_10000", "time": 8.762469, "empty_cells": 35, "round": 4}, {"id": 2, "player": "PAB_3", "time": 0.026943, "empty_cells": 34, "round": 5}, {"id": 2, "player": "MCTS_10000", "time": 8.346938, "empty_cells": 33, "round": 5}, {"id": 2, "player": "PAB_3", "time": 0.025794, "empty_cells": 32, "round": 6}, {"id": 2, "player": "MCTS_10000", "time": 8.501601, "empty_cells": 31, "round": 6}, {"id": 2, "player": "PAB_3", "time": 0.030877, "empty_cells": 30, "round": 7}, {"id": 2, "player": "MCTS_10000", "time": 7.592953, "empty_cells": 29, "round": 7}, {"id": 2, "player": "PAB_3", "time": 0.028111, "empty_cells": 28, "round": 8}, {"id": 2, "player": "MCTS_10000", "time": 7.378549, "empty_cells": 27, "round": 8}, {"id": 2, "player": "PAB_3", "time": 0.023961, "empty_cells": 26, "round": 9}, {"id": 2, "player": "MCTS_10000", "time": 6.755623, "empty_cells": 25, "round": 9}, {"id": 2, "player": "PAB_3", "time": 0.028481, "empty_cells": 24, "round": 10}, {"id": 2, "player": "MCTS_10000", "time": 4.305779, "empty_cells": 23, "round": 10}, {"id": 2, "player": "PAB_3", "time": 0.023624, "empty_cells": 22, "round": 11}, {"id": 2, "player": "MCTS_10000", "time": 3.399711, "empty_cells": 21, "round": 11}, {"id": 2, "player": "PAB_3", "time": 0.009544, "empty_cells": 20, "round": 12}, {"id": 2, "player": "MCTS_10000", "time": 2.774928, "empty_cells": 19, "round": 12}, {"id": 2, "player": "PAB_3", "time": 0.011364, "empty_cells": 18, "round": 13}, {"id": 2, "player": "MCTS_10000", "time": 1.273095, "empty_cells": 17, "round": 13}, {"id": 2, "player": "PAB_3", "time": 0.009206, "empty_cells": 16, "round": 14}, {"id": 2, "player": "MCTS_10000", "time": 1.045795, "empty_cells": 15, "round": 14}, {"id": 2, "player": "PAB_3", "time": 0.004777, "empty_cells": 14, "round": 15}, {"id": 2, "player": "MCTS_10000", "time": 0.542443, "empty_cells": 13, "round": 15}, {"id": 2, "player": "PAB_3", "time": 0.00163, "empty_cells": 12, "round": 16}, {"id": 2, "player": "MCTS_10000", "time": 0.520695, "empty_cells": 11, "round": 16}, {"id": 3, "player": "PAB_3", "time": 0.035795, "empty_cells": 42, "round": 1}, {"id": 3, "player": "MCTS_10000", "time": 10.61273, "empty_cells": 41, "round": 1}, {"id": 3, "player": "PAB_3", "time": 0.032439, "empty_cells": 40, "round": 2}, {"id": 3, "player": "MCTS_10000", "time": 9.697645, "empty_cells": 39, "round": 2}, {"id": 3, "player": "PAB_3", "time": 0.038518, "empty_cells": 38, "round": 3}, {"id": 3, "player": "MCTS_10000", "time": 9.34378, "empty_cells": 37, "round": 3}, {"id": 3, "player": "PAB_3", "time": 0.046458, "empty_cells": 36, "round": 4}, {"id": 3, "player": "MCTS_10000", "time": 9.15671, "empty_cells": 35, "round": 4}, {"id": 3, "player": "PAB_3", "time": 0.030486, "empty_cells": 34, "round": 5}, {"id": 3, "player": "MCTS_10000", "time": 8.449459, "empty_cells": 33, "round": 5}, {"id": 3, "player": "PAB_3", "time": 0.025889, "empty_cells": 32, "round": 6}, {"id": 3, "player": "MCTS_10000", "time": 8.430544, "empty_cells": 31, "round": 6}, {"id": 3, "player": "PAB_3", "time": 0.035244, "empty_cells": 30, "round": 7}, {"id": 3, "player": "MCTS_10000", "time": 8.413253, "empty_cells": 29, "round": 7}, {"id": 3, "player": "PAB_3", "time": 0.028289, "empty_cells": 28, "round": 8}, {"id": 3, "player": "MCTS_10000", "time": 6.636598, "empty_cells": 27, "round": 8}, {"id": 3, "player": "PAB_3", "time": 0.029734, "empty_cells": 26, "round": 9}, {"id": 3, "player": "MCTS_10000", "time": 5.682865, "empty_cells": 25, "round": 9}, {"id": 3, "player": "PAB_3", "time": 0.018336, "empty_cells": 24, "round": 10}, {"id": 3, "player": "MCTS_10000", "time": 5.178503, "empty_cells": 23, "round": 10}, {"id": 3, "player": "PAB_3", "time": 0.018742, "empty_cells": 22, "round": 11}, {"id": 3, "player": "MCTS_10000", "time": 2.926901, "empty_cells": 21, "round": 11}, {"id": 3, "player": "PAB_3", "time": 0.011316, "empty_cells": 20, "round": 12}, {"id": 3, "player": "MCTS_10000", "time": 2.10138, "empty_cells": 19, "round": 12}, {"id": 3, "player": "PAB_3", "time": 0.005761, "empty_cells": 18, "round": 13}, {"id": 3, "player": "MCTS_10000", "time": 1.760667, "empty_cells": 17, "round": 13}, {"id": 3, "player": "PAB_3", "time": 0.010498, "empty_cells": 16, "round": 14}, {"id": 3, "player": "MCTS_10000", "time": 1.259952, "empty_cells": 15, "round": 14}, {"id": 3, "player": "PAB_3", "time": 0.00638, "empty_cells": 14, "round": 15}, {"id": 3, "player": "MCTS_10000", "time": 0.795539, "empty_cells": 13, "round": 15}, {"id": 3, "player": "PAB_3", "time": 0.002313, "empty_cells": 12, "round": 16}, {"id": 3, "player": "MCTS_10000", "time": 0.496333, "empty_cells": 11, "round": 16}, {"id": 3, "player": "PAB_3", "time": 0.001096, "empty_cells": 10, "round": 17}, {"id": 4, "player": "PAB_3", "time": 0.038224, "empty_cells": 42, "round": 1}, {"id": 4, "player": "MCTS_10000", "time": 10.499933, "empty_cells": 41, "round": 1}, {"id": 4, "player": "PAB_3", "time": 0.029919, "empty_cells": 40, "round": 2}, {"id": 4, "player": "MCTS_10000", "time": 9.94074, "empty_cells": 39, "round": 2}, {"id": 4, "player": "PAB_3", "time": 0.048421, "empty_cells": 38, "round": 3}, {"id": 4, "player": "MCTS_10000", "time": 10.408294, "empty_cells": 37, "round": 3}, {"id": 4, "player": "PAB_3", "time": 0.040915, "empty_cells": 36, "round": 4}, {"id": 4, "player": "MCTS_10000", "time": 9.929467, "empty_cells": 35, "round": 4}, {"id": 4, "player": "PAB_3", "time": 0.044794, "empty_cells": 34, "round": 5}, {"id": 4, "player": "MCTS_10000", "time": 9.768304, "empty_cells": 33, "round": 5}, {"id": 4, "player": "PAB_3", "time": 0.032661, "empty_cells": 32, "round": 6}, {"id": 4, "player": "MCTS_10000", "time": 6.602565, "empty_cells": 31, "round": 6}, {"id": 4, "player": "PAB_3", "time": 0.05386, "empty_cells": 30, "round": 7}, {"id": 4, "player": "MCTS_10000", "time": 6.507029, "empty_cells": 29, "round": 7}, {"id": 4, "player": "PAB_3", "time": 0.041903, "empty_cells": 28, "round": 8}, {"id": 4, "player": "MCTS_10000", "time": 5.155079, "empty_cells": 27, "round": 8}, {"id": 4, "player": "PAB_3", "time": 0.038682, "empty_cells": 26, "round": 9}, {"id": 4, "player": "MCTS_10000", "time": 5.971801, "empty_cells": 25, "round": 9}, {"id": 4, "player": "PAB_3", "time": 0.021472, "empty_cells": 24, "round": 10}, {"id": 4, "player": "MCTS_10000", "time": 4.199103, "empty_cells": 23, "round": 10}, {"id": 4, "player": "PAB_3", "time": 0.023334, "empty_cells": 22, "round": 11}, {"id": 4, "player": "MCTS_10000", "time": 3.414002, "empty_cells": 21, "round": 11}, {"id": 4, "player": "PAB_3", "time": 0.012026, "empty_cells": 20, "round": 12}, {"id": 4, "player": "MCTS_10000", "time": 3.121631, "empty_cells": 19, "round": 12}, {"id": 4, "player": "PAB_3", "time": 0.020558, "empty_cells": 18, "round": 13}, {"id": 4, "player": "MCTS_10000", "time": 2.419369, "empty_cells": 17, "round": 13}, {"id": 4, "player": "PAB_3", "time": 0.017633, "empty_cells": 16, "round": 14}, {"id": 4, "player": "MCTS_10000", "time": 2.105038, "empty_cells": 15, "round": 14}, {"id": 4, "player": "PAB_3", "time": 0.011858, "empty_cells": 14, "round": 15}, {"id": 4, "player": "MCTS_10000", "time": 1.426048, "empty_cells": 13, "round": 15}, {"id": 4, "player": "PAB_3", "time": 0.010419, "empty_cells": 12, "round": 16}, {"id": 4, "player": "MCTS_10000", "time": 0.954995, "empty_cells": 11, "round": 16}, {"id": 4, "player": "PAB_3", "time": 0.006005, "empty_cells": 10, "round": 17}, {"id": 4, "player": "MCTS_10000", "time": 0.688587, "empty_cells": 9, "round": 17}, {"id": 4, "player": "PAB_3", "time": 0.001735, "empty_cells": 8, "round": 18}, {"id": 4, "player": "MCTS_10000", "time": 0.681647, "empty_cells": 7, "round": 18}, {"id": 4, "player": "PAB_3", "time": 0.000386, "empty_cells": 6, "round": 19}, {"id": 4, "player": "MCTS_10000", "time": 0.650338, "empty_cells": 5, "round": 19}, {"id": 5, "player": "PAB_3", "time": 0.034622, "empty_cells": 42, "round": 1}, {"id": 5, "player": "MCTS_10000", "time": 10.359089, "empty_cells": 41, "round": 1}, {"id": 5, "player": "PAB_3", "time": 0.035908, "empty_cells": 40, "round": 2}, {"id": 5, "player": "MCTS_10000", "time": 9.91405, "empty_cells": 39, "round": 2}, {"id": 5, "player": "PAB_3", "time": 0.039556, "empty_cells": 38, "round": 3}, {"id": 5, "player": "MCTS_10000", "time": 9.480459, "empty_cells": 37, "round": 3}, {"id": 5, "player": "PAB_3", "time": 0.039368, "empty_cells": 36, "round": 4}, {"id": 5, "player": "MCTS_10000", "time": 9.035356, "empty_cells": 35, "round": 4}, {"id": 5, "player": "PAB_3", "time": 0.046329, "empty_cells": 34, "round": 5}, {"id": 5, "player": "MCTS_10000", "time": 8.676481, "empty_cells": 33, "round": 5}, {"id": 5, "player": "PAB_3", "time": 0.031652, "empty_cells": 32, "round": 6}, {"id": 5, "player": "MCTS_10000", "time": 6.585247, "empty_cells": 31, "round": 6}, {"id": 5, "player": "PAB_3", "time": 0.0535, "empty_cells": 30, "round": 7}, {"id": 5, "player": "MCTS_10000", "time": 6.164435, "empty_cells": 29, "round": 7}, {"id": 5, "player": "PAB_3", "time": 0.038594, "empty_cells": 28, "round": 8}, {"id": 5, "player": "MCTS_10000", "time": 5.305787, "empty_cells": 27, "round": 8}, {"id": 5, "player": "PAB_3", "time": 0.040014, "empty_cells": 26, "round": 9}, {"id": 5, "player": "MCTS_10000", "time": 5.700887, "empty_cells": 25, "round": 9}, {"id": 5, "player": "PAB_3", "time": 0.021311, "empty_cells": 24, "round": 10}, {"id": 5, "player": "MCTS_10000", "time": 4.521112, "empty_cells": 23, "round": 10}, {"id": 5, "player": "PAB_3", "time": 0.023253, "empty_cells": 22, "round": 11}, {"id": 5, "player": "MCTS_10000", "time": 3.400272, "empty_cells": 21, "round": 11}, {"id": 5, "player": "PAB_3", "time": 0.011973, "empty_cells": 20, "round": 12}, {"id": 5, "player": "MCTS_10000", "time": 3.175592, "empty_cells": 19, "round": 12}, {"id": 5, "player": "PAB_3", "time": 0.018037, "empty_cells": 18, "round": 13}, {"id": 5, "player": "MCTS_10000", "time": 2.718802, "empty_cells": 17, "round": 13}, {"id": 5, "player": "PAB_3", "time": 0.017135, "empty_cells": 16, "round": 14}, {"id": 5, "player": "MCTS_10000", "time": 2.190264, "empty_cells": 15, "round": 14}, {"id": 5, "player": "PAB_3", "time": 0.011428, "empty_cells": 14, "round": 15}, {"id": 5, "player": "MCTS_10000", "time": 1.336536, "empty_cells": 13, "round": 15}, {"id": 5, "player": "PAB_3", "time": 0.010511, "empty_cells": 12, "round": 16}, {"id": 5, "player": "MCTS_10000", "time": 0.94861, "empty_cells": 11, "round": 16}, {"id": 5, "player": "PAB_3", "time": 0.006124, "empty_cells": 10, "round": 17}, {"id": 5, "player": "MCTS_10000", "time": 0.688471, "empty_cells": 9, "round": 17}, {"id": 5, "player": "PAB_3", "time": 0.001784, "empty_cells": 8, "round": 18}, {"id": 5, "player": "MCTS_10000", "time": 0.679569, "empty_cells": 7, "round": 18}, {"id": 5, "player": "PAB_3", "time": 0.00039, "empty_cells": 6, "round": 19}, {"id": 5, "player": "MCTS_10000", "time": 0.646315, "empty_cells": 5, "round": 19}, {"id": 6, "player": "MCTS_10000", "time": 9.912697, "empty_cells": 42, "round": 1}, {"id": 6, "player": "PAB_3", "time": 0.030588, "empty_cells": 41, "round": 1}, {"id": 6, "player": "MCTS_10000", "time": 9.900359, "empty_cells": 40, "round": 2}, {"id": 6, "player": "PAB_3", "time": 0.029201, "empty_cells": 39, "round": 2}, {"id": 6, "player": "MCTS_10000", "time": 9.089032, "empty_cells": 38, "round": 3}, {"id": 6, "player": "PAB_3", "time": 0.033303, "empty_cells": 37, "round": 3}, {"id": 6, "player": "MCTS_10000", "time": 9.573976, "empty_cells": 36, "round": 4}, {"id": 6, "player": "PAB_3", "time": 0.042608, "empty_cells": 35, "round": 4}, {"id": 6, "player": "MCTS_10000", "time": 7.944033, "empty_cells": 34, "round": 5}, {"id": 6, "player": "PAB_3", "time": 0.040402, "empty_cells": 33, "round": 5}, {"id": 6, "player": "MCTS_10000", "time": 6.630152, "empty_cells": 32, "round": 6}, {"id": 6, "player": "PAB_3", "time": 0.046714, "empty_cells": 31, "round": 6}, {"id": 6, "player": "MCTS_10000", "time": 6.987344, "empty_cells": 30, "round": 7}, {"id": 6, "player": "PAB_3", "time": 0.04357, "empty_cells": 29, "round": 7}, {"id": 6, "player": "MCTS_10000", "time": 6.023319, "empty_cells": 28, "round": 8}, {"id": 6, "player": "PAB_3", "time": 0.041392, "empty_cells": 27, "round": 8}, {"id": 6, "player": "MCTS_10000", "time": 5.633972, "empty_cells": 26, "round": 9}, {"id": 6, "player": "PAB_3", "time": 0.026441, "empty_cells": 25, "round": 9}, {"id": 6, "player": "MCTS_10000", "time": 4.999169, "empty_cells": 24, "round": 10}, {"id": 6, "player": "PAB_3", "time": 0.015253, "empty_cells": 23, "round": 10}, {"id": 6, "player": "MCTS_10000", "time": 4.489983, "empty_cells": 22, "round": 11}, {"id": 6, "player": "PAB_3", "time": 0.011327, "empty_cells": 21, "round": 11}, {"id": 6, "player": "MCTS_10000", "time": 3.662559, "empty_cells": 20, "round": 12}, {"id": 6, "player": "PAB_3", "time": 0.011045, "empty_cells": 19, "round": 12}, {"id": 6, "player": "MCTS_10000", "time": 2.671707, "empty_cells": 18, "round": 13}, {"id": 6, "player": "PAB_3", "time": 0.021111, "empty_cells": 17, "round": 13}, {"id": 6, "player": "MCTS_10000", "time": 2.311979, "empty_cells": 16, "round": 14}, {"id": 6, "player": "PAB_3", "time": 0.023213, "empty_cells": 15, "round": 14}, {"id": 6, "player": "MCTS_10000", "time": 1.363889, "empty_cells": 14, "round": 15}, {"id": 6, "player": "PAB_3", "time": 0.016706, "empty_cells": 13, "round": 15}, {"id": 6, "player": "MCTS_10000", "time": 0.873574, "empty_cells": 12, "round": 16}, {"id": 6, "player": "PAB_3", "time": 0.013235, "empty_cells": 11, "round": 16}, {"id": 7, "player": "MCTS_10000", "time": 10.160775, "empty_cells": 42, "round": 1}, {"id": 7, "player": "PAB_3", "time": 0.031996, "empty_cells": 41, "round": 1}, {"id": 7, "player": "MCTS_10000", "time": 9.688406, "empty_cells": 40, "round": 2}, {"id": 7, "player": "PAB_3", "time": 0.028938, "empty_cells": 39, "round": 2}, {"id": 7, "player": "MCTS_10000", "time": 9.185474, "empty_cells": 38, "round": 3}, {"id": 7, "player": "PAB_3", "time": 0.041086, "empty_cells": 37, "round": 3}, {"id": 7, "player": "MCTS_10000", "time": 9.376394, "empty_cells": 36, "round": 4}, {"id": 7, "player": "PAB_3", "time": 0.023905, "empty_cells": 35, "round": 4}, {"id": 7, "player": "MCTS_10000", "time": 8.686398, "empty_cells": 34, "round": 5}, {"id": 7, "player": "PAB_3", "time": 0.032928, "empty_cells": 33, "round": 5}, {"id": 7, "player": "MCTS_10000", "time": 7.035798, "empty_cells": 32, "round": 6}, {"id": 7, "player": "PAB_3", "time": 0.044622, "empty_cells": 31, "round": 6}, {"id": 7, "player": "MCTS_10000", "time": 3.086664, "empty_cells": 30, "round": 7}, {"id": 7, "player": "PAB_3", "time": 0.032897, "empty_cells": 29, "round": 7}, {"id": 7, "player": "MCTS_10000", "time": 1.831791, "empty_cells": 28, "round": 8}, {"id": 8, "player": "MCTS_10000", "time": 9.738988, "empty_cells": 42, "round": 1}, {"id": 8, "player": "PAB_3", "time": 0.031526, "empty_cells": 41, "round": 1}, {"id": 8, "player": "MCTS_10000", "time": 9.792919, "empty_cells": 40, "round": 2}, {"id": 8, "player": "PAB_3", "time": 0.028992, "empty_cells": 39, "round": 2}, {"id": 8, "player": "MCTS_10000", "time": 9.323051, "empty_cells": 38, "round": 3}, {"id": 8, "player": "PAB_3", "time": 0.033504, "empty_cells": 37, "round": 3}, {"id": 8, "player": "MCTS_10000", "time": 9.920466, "empty_cells": 36, "round": 4}, {"id": 8, "player": "PAB_3", "time": 0.043474, "empty_cells": 35, "round": 4}, {"id": 8, "player": "MCTS_10000", "time": 8.221918, "empty_cells": 34, "round": 5}, {"id": 8, "player": "PAB_3", "time": 0.040281, "empty_cells": 33, "round": 5}, {"id": 8, "player": "MCTS_10000", "time": 6.781299, "empty_cells": 32, "round": 6}, {"id": 8, "player": "PAB_3", "time": 0.049916, "empty_cells": 31, "round": 6}, {"id": 8, "player": "MCTS_10000", "time": 5.888209, "empty_cells": 30, "round": 7}, {"id": 8, "player": "PAB_3", "time": 0.026395, "empty_cells": 29, "round": 7}, {"id": 8, "player": "MCTS_10000", "time": 6.291699, "empty_cells": 28, "round": 8}, {"id": 8, "player": "PAB_3", "time": 0.027867, "empty_cells": 27, "round": 8}, {"id": 8, "player": "MCTS_10000", "time": 5.155698, "empty_cells": 26, "round": 9}, {"id": 8, "player": "PAB_3", "time": 0.020309, "empty_cells": 25, "round": 9}, {"id": 8, "player": "MCTS_10000", "time": 4.849278, "empty_cells": 24, "round": 10}, {"id": 8, "player": "PAB_3", "time": 0.014474, "empty_cells": 23, "round": 10}, {"id": 8, "player": "MCTS_10000", "time": 3.521636, "empty_cells": 22, "round": 11}, {"id": 8, "player": "PAB_3", "time": 0.009162, "empty_cells": 21, "round": 11}, {"id": 8, "player": "MCTS_10000", "time": 2.702709, "empty_cells": 20, "round": 12}, {"id": 8, "player": "PAB_3", "time": 0.008891, "empty_cells": 19, "round": 12}, {"id": 8, "player": "MCTS_10000", "time": 2.415374, "empty_cells": 18, "round": 13}, {"id": 8, "player": "PAB_3", "time": 0.009278, "empty_cells": 17, "round": 13}, {"id": 8, "player": "MCTS_10000", "time": 1.85529, "empty_cells": 16, "round": 14}, {"id": 8, "player": "PAB_3", "time": 0.004652, "empty_cells": 15, "round": 14}, {"id": 8, "player": "MCTS_10000", "time": 1.056106, "empty_cells": 14, "round": 15}, {"id": 8, "player": "PAB_3", "time": 0.061764, "empty_cells": 13, "round": 15}, {"id": 8, "player": "MCTS_10000", "time": 1.102724, "empty_cells": 12, "round": 16}, {"id": 8, "player": "PAB_3", "time": 0.005525, "empty_cells": 11, "round": 16}, {"id": 8, "player": "MCTS_10000", "time": 0.936803, "empty_cells": 10, "round": 17}, {"id": 8, "player": "PAB_3", "time": 0.00593, "empty_cells": 9, "round": 17}, {"id": 8, "player": "MCTS_10000", "time": 0.762712, "empty_cells": 8, "round": 18}, {"id": 8, "player": "PAB_3", "time": 0.006143, "empty_cells": 7, "round": 18}, {"id": 8, "player": "MCTS_10000", "time": 0.631281, "empty_cells": 6, "round": 19}, {"id": 8, "player": "PAB_3", "time": 0.003125, "empty_cells": 5, "round": 19}, {"id": 9, "player": "MCTS_10000", "time": 10.150806, "empty_cells": 42, "round": 1}, {"id": 9, "player": "PAB_3", "time": 0.030705, "empty_cells": 41, "round": 1}, {"id": 9, "player": "MCTS_10000", "time": 9.819384, "empty_cells": 40, "round": 2}, {"id": 9, "player": "PAB_3", "time": 0.032259, "empty_cells": 39, "round": 2}, {"id": 9, "player": "MCTS_10000", "time": 8.730928, "empty_cells": 38, "round": 3}, {"id": 9, "player": "PAB_3", "time": 0.033513, "empty_cells": 37, "round": 3}, {"id": 9, "player": "MCTS_10000", "time": 9.556326, "empty_cells": 36, "round": 4}, {"id": 9, "player": "PAB_3", "time": 0.043276, "empty_cells": 35, "round": 4}, {"id": 9, "player": "MCTS_10000", "time": 8.012407, "empty_cells": 34, "round": 5}, {"id": 9, "player": "PAB_3", "time": 0.040405, "empty_cells": 33, "round": 5}, {"id": 9, "player": "MCTS_10000", "time": 6.442788, "empty_cells": 32, "round": 6}, {"id": 9, "player": "PAB_3", "time": 0.046414, "empty_cells": 31, "round": 6}, {"id": 9, "player": "MCTS_10000", "time": 6.877438, "empty_cells": 30, "round": 7}, {"id": 9, "player": "PAB_3", "time": 0.042331, "empty_cells": 29, "round": 7}, {"id": 9, "player": "MCTS_10000", "time": 6.172723, "empty_cells": 28, "round": 8}, {"id": 9, "player": "PAB_3", "time": 0.041776, "empty_cells": 27, "round": 8}, {"id": 9, "player": "MCTS_10000", "time": 5.548569, "empty_cells": 26, "round": 9}, {"id": 9, "player": "PAB_3", "time": 0.025501, "empty_cells": 25, "round": 9}, {"id": 9, "player": "MCTS_10000", "time": 4.882581, "empty_cells": 24, "round": 10}, {"id": 9, "player": "PAB_3", "time": 0.015171, "empty_cells": 23, "round": 10}, {"id": 9, "player": "MCTS_10000", "time": 4.352471, "empty_cells": 22, "round": 11}, {"id": 9, "player": "PAB_3", "time": 0.021426, "empty_cells": 21, "round": 11}, {"id": 9, "player": "MCTS_10000", "time": 2.74635, "empty_cells": 20, "round": 12}, {"id": 9, "player": "PAB_3", "time": 0.009659, "empty_cells": 19, "round": 12}, {"id": 9, "player": "MCTS_10000", "time": 2.41384, "empty_cells": 18, "round": 13}, {"id": 9, "player": "PAB_3", "time": 0.011569, "empty_cells": 17, "round": 13}, {"id": 9, "player": "MCTS_10000", "time": 2.040951, "empty_cells": 16, "round": 14}, {"id": 9, "player": "PAB_3", "time": 0.009554, "empty_cells": 15, "round": 14}, {"id": 9, "player": "MCTS_10000", "time": 1.033599, "empty_cells": 14, "round": 15}, {"id": 9, "player": "PAB_3", "time": 0.007656, "empty_cells": 13, "round": 15}, {"id": 9, "player": "MCTS_10000", "time": 1.025317, "empty_cells": 12, "round": 16}, {"id": 9, "player": "PAB_3", "time": 0.001644, "empty_cells": 11, "round": 16}, {"id": 9, "player": "MCTS_10000", "time": 0.935769, "empty_cells": 10, "round": 17}, {"id": 9, "player": "PAB_3", "time": 0.002981, "empty_cells": 9, "round": 17}, {"id": 9, "player": "MCTS_10000", "time": 0.58976, "empty_cells": 8, "round": 18}, {"id": 10, "player": "MCTS_10000", "time": 9.910724, "empty_cells": 42, "round": 1}, {"id": 10, "player": "PAB_3", "time": 0.02903, "empty_cells": 41, "round": 1}, {"id": 10, "player": "MCTS_10000", "time": 9.682007, "empty_cells": 40, "round": 2}, {"id": 10, "player": "PAB_3", "time": 0.027419, "empty_cells": 39, "round": 2}, {"id": 10, "player": "MCTS_10000", "time": 9.082572, "empty_cells": 38, "round": 3}, {"id": 10, "player": "PAB_3", "time": 0.033479, "empty_cells": 37, "round": 3}, {"id": 10, "player": "MCTS_10000", "time": 9.679947, "empty_cells": 36, "round": 4}, {"id": 10, "player": "PAB_3", "time": 0.048305, "empty_cells": 35, "round": 4}, {"id": 10, "player": "MCTS_10000", "time": 8.639471, "empty_cells": 34, "round": 5}, {"id": 10, "player": "PAB_3", "time": 0.043818, "empty_cells": 33, "round": 5}, {"id": 10, "player": "MCTS_10000", "time": 5.595571, "empty_cells": 32, "round": 6}, {"id": 10, "player": "PAB_3", "time": 0.045067, "empty_cells": 31, "round": 6}, {"id": 10, "player": "MCTS_10000", "time": 6.413988, "empty_cells": 30, "round": 7}, {"id": 10, "player": "PAB_3", "time": 0.043004, "empty_cells": 29, "round": 7}, {"id": 10, "player": "MCTS_10000", "time": 5.725237, "empty_cells": 28, "round": 8}, {"id": 10, "player": "PAB_3", "time": 0.040222, "empty_cells": 27, "round": 8}, {"id": 10, "player": "MCTS_10000", "time": 5.42709, "empty_cells": 26, "round": 9}, {"id": 10, "player": "PAB_3", "time": 0.024911, "empty_cells": 25, "round": 9}, {"id": 10, "player": "MCTS_10000", "time": 4.563621, "empty_cells": 24, "round": 10}, {"id": 10, "player": "PAB_3", "time": 0.014424, "empty_cells": 23, "round": 10}, {"id": 10, "player": "MCTS_10000", "time": 4.305341, "empty_cells": 22, "round": 11}, {"id": 10, "player": "PAB_3", "time": 0.028827, "empty_cells": 21, "round": 11}, {"id": 10, "player": "MCTS_10000", "time": 3.37213, "empty_cells": 20, "round": 12}, {"id": 10, "player": "PAB_3", "time": 0.019741, "empty_cells": 19, "round": 12}, {"id": 10, "player": "MCTS_10000", "time": 2.826424, "empty_cells": 18, "round": 13}, {"id": 10, "player": "PAB_3", "time": 0.016109, "empty_cells": 17, "round": 13}, {"id": 10, "player": "MCTS_10000", "time": 1.979043, "empty_cells": 16, "round": 14}, {"id": 10, "player": "PAB_3", "time": 0.007216, "empty_cells": 15, "round": 14}, {"id": 10, "player": "MCTS_10000", "time": 1.278906, "empty_cells": 14, "round": 15}, {"id": 10, "player": "PAB_3", "time": 0.004828, "empty_cells": 13, "round": 15}, {"id": 10, "player": "MCTS_10000", "time": 0.998734, "empty_cells": 12, "round": 16}, {"id": 10, "player": "PAB_3", "time": 0.008049, "empty_cells": 11, "round": 16}, {"id": 10, "player": "MCTS_10000", "time": 0.862597, "empty_cells": 10, "round": 17}, {"id": 10, "player": "PAB_3", "time": 0.005925, "empty_cells": 9, "round": 17}]